leep/__init__.py
leep/__version__.py
leep/base.py
leep/build_rom.py
leep/ca.py
leep/cli.py
leep/file.py
leep/logic.py
leep/raw.py
leep/eng/BinaryUpdate.bob
leep/eng/TextEntry.bob
leep/eng/TextUpdate.bob
leep/eng/__init__.py
leep/eng/__main__.py
leep/eng/base.bob
leep/test/__init__.py
leep/test/test_base.py
leep/test/test_ca.py
leep/test/test_cli.py
leep/test/test_raw.py
leep-1.0.0a4.dist-info/licenses/LICENSE.md
leep-1.0.0a4.dist-info/METADATA
leep-1.0.0a4.dist-info/WHEEL
leep-1.0.0a4.dist-info/entry_points.txt
leep-1.0.0a4.dist-info/top_level.txt
leep-1.0.0a4.dist-info/RECORD
