Metadata-Version: 2.4
Name: leep
Version: 1.0.0a4
Summary: LBNL Embedded Ethernet Protocol tooling
Author-email: Michael Davidsaver <mdavidsaver@gmail.com>
License: LBNL Embedded Ethernet Protocol library (LEEP) Copyright (c) 2025,
Project-URL: Homepage, https://gitlab.lbl.gov/drivers/leep
Project-URL: Issues, https://gitlab.lbl.gov/drivers/leep/issues
Classifier: Programming Language :: Python :: 2
Classifier: Programming Language :: Python :: 3
Classifier: License :: OSI Approved :: BSD License
Classifier: Operating System :: OS Independent
License-File: LICENSE.md
Requires-Dist: cothread
Requires-Dist: numpy
Requires-Dist: matplotlib
Dynamic: license-file
